LICENSE
README.md
setup.py
lamadava/__init__.py
lamadava/__version__.py
lamadava/api.py
lamadava/asyncapi.py
lamadava/base.py
lamadava.egg-info/PKG-INFO
lamadava.egg-info/SOURCES.txt
lamadava.egg-info/dependency_links.txt
lamadava.egg-info/requires.txt
lamadava.egg-info/top_level.txt